README.md
setup.py
lbrlabs_pulumi_nxos/__init__.py
lbrlabs_pulumi_nxos/_inputs.py
lbrlabs_pulumi_nxos/_utilities.py
lbrlabs_pulumi_nxos/bgp.py
lbrlabs_pulumi_nxos/bgp_address_family.py
lbrlabs_pulumi_nxos/bgp_advertised_prefix.py
lbrlabs_pulumi_nxos/bgp_graceful_restart.py
lbrlabs_pulumi_nxos/bgp_instance.py
lbrlabs_pulumi_nxos/bgp_peer.py
lbrlabs_pulumi_nxos/bgp_peer_address_family.py
lbrlabs_pulumi_nxos/bgp_peer_address_family_prefix_list_control.py
lbrlabs_pulumi_nxos/bgp_peer_address_family_route_control.py
lbrlabs_pulumi_nxos/bgp_peer_template.py
lbrlabs_pulumi_nxos/bgp_peer_template_address_family.py
lbrlabs_pulumi_nxos/bgp_peer_template_max_prefix.py
lbrlabs_pulumi_nxos/bgp_route_control.py
lbrlabs_pulumi_nxos/bgp_vrf.py
lbrlabs_pulumi_nxos/bridge_domain.py
lbrlabs_pulumi_nxos/default_qos_class_map.py
lbrlabs_pulumi_nxos/default_qos_class_map_dscp.py
lbrlabs_pulumi_nxos/default_qos_policy_interface_in.py
lbrlabs_pulumi_nxos/default_qos_policy_interface_in_policy_map.py
lbrlabs_pulumi_nxos/default_qos_policy_map.py
lbrlabs_pulumi_nxos/default_qos_policy_map_match_class_map.py
lbrlabs_pulumi_nxos/default_qos_policy_map_match_class_map_police.py
lbrlabs_pulumi_nxos/default_qos_policy_map_match_class_map_set_qos_group.py
lbrlabs_pulumi_nxos/dhcp_relay_address.py
lbrlabs_pulumi_nxos/dhcp_relay_interface.py
lbrlabs_pulumi_nxos/ethernet.py
lbrlabs_pulumi_nxos/evpn.py
lbrlabs_pulumi_nxos/evpn_vni.py
lbrlabs_pulumi_nxos/evpn_vni_route_target.py
lbrlabs_pulumi_nxos/evpn_vni_route_target_direction.py
lbrlabs_pulumi_nxos/feature_bfd.py
lbrlabs_pulumi_nxos/feature_bgp.py
lbrlabs_pulumi_nxos/feature_dhcp.py
lbrlabs_pulumi_nxos/feature_evpn.py
lbrlabs_pulumi_nxos/feature_hmm.py
lbrlabs_pulumi_nxos/feature_hsrp.py
lbrlabs_pulumi_nxos/feature_interface_vlan.py
lbrlabs_pulumi_nxos/feature_isis.py
lbrlabs_pulumi_nxos/feature_lacp.py
lbrlabs_pulumi_nxos/feature_lldp.py
lbrlabs_pulumi_nxos/feature_macsec.py
lbrlabs_pulumi_nxos/feature_netflow.py
lbrlabs_pulumi_nxos.egg-info/PKG-INFO
lbrlabs_pulumi_nxos.egg-info/SOURCES.txt
lbrlabs_pulumi_nxos.egg-info/dependency_links.txt
lbrlabs_pulumi_nxos.egg-info/not-zip-safe
lbrlabs_pulumi_nxos.egg-info/requires.txt
lbrlabs_pulumi_nxos.egg-info/top_level.txt
