Metadata-Version: 2.1
Name: lbrlabs-pulumi-nxos
Version: 0.0.2
Summary: A Pulumi package for creating and managing Cisco nxos XE Devices.
Home-page: https://www.pulumi.com
License: Apache-2.0
Project-URL: Repository, https://github.com/lbrlabs/pulumi-nxos
Keywords: pulumi nxos category/utility
Platform: UNKNOWN
Requires-Python: >=3.7
